README.md
setup.py
EAGM/__init__.py
EAGM/main.py
EAGM.egg-info/PKG-INFO
EAGM.egg-info/SOURCES.txt
EAGM.egg-info/dependency_links.txt
EAGM.egg-info/requires.txt
EAGM.egg-info/top_level.txt