Metadata-Version: 2.1
Name: EAGM
Version: 1.0.1
Summary: A simple API wrapper for Discord Add Guild Member
Home-page: https://github.com/taka-4602/Discord-Easy-Add-Guild-Member
Author: taka4602
Author-email: shun4602@gmail.com
Keywords: discord,add member
Classifier: Programming Language :: Python :: 3
Classifier: License :: OSI Approved :: MIT License
Classifier: Operating System :: OS Independent
Requires-Python: >=3.6
